LICENSE
MANIFEST.in
README.rst
setup.cfg
setup.py
flake8_class_newline/__init__.py
flake8_class_newline/__version__.py
flake8_class_newline.egg-info/PKG-INFO
flake8_class_newline.egg-info/SOURCES.txt
flake8_class_newline.egg-info/dependency_links.txt
flake8_class_newline.egg-info/entry_points.txt
flake8_class_newline.egg-info/requires.txt
flake8_class_newline.egg-info/top_level.txt
flake8_class_newline.egg-info/zip-safe
tests/__init__.py
tests/test_checks.py