Metadata-Version: 1.1
Name: flake8-class-newline
Version: 1.2.0
Summary: Flake8 lint for newline after class definitions.
Home-page: UNKNOWN
Author: Alexander van Eck
Author-email: alex@x-all.nl
License: MIT
Keywords: flake8 lint class new line
Platform: UNKNOWN
Classifier: Development Status :: 3 - Alpha
Classifier: Environment :: Console
Classifier: Intended Audience :: Developers
Classifier: Operating System :: OS Independent
Classifier: License :: OSI Approved :: MIT License
Classifier: Programming Language :: Python
Classifier: Programming Language :: Python :: 2
Classifier: Programming Language :: Python :: 2.7
Classifier: Programming Language :: Python :: 3
Classifier: Programming Language :: Python :: 3.4
Classifier: Topic :: Software Development :: Libraries :: Python Modules
Classifier: Topic :: Software Development :: Quality Assurance
